mbonig/nightynight/__init__.py
mbonig/nightynight/py.typed
mbonig/nightynight/_jsii/__init__.py
mbonig/nightynight/_jsii/nightynight@2.0.4.jsii.tgz
mbonig.nightynight-2.0.4.dist-info/LICENSE
mbonig.nightynight-2.0.4.dist-info/METADATA
mbonig.nightynight-2.0.4.dist-info/WHEEL
mbonig.nightynight-2.0.4.dist-info/top_level.txt
mbonig.nightynight-2.0.4.dist-info/RECORD
